easywsl/__init__.py
easywsl/__main__.py
easywsl/forward.py
easywsl/utils.py
easywsl/wsl.py
easywsl-0.1.2.dist-info/METADATA
easywsl-0.1.2.dist-info/WHEEL
easywsl-0.1.2.dist-info/entry_points.txt
easywsl-0.1.2.dist-info/top_level.txt
easywsl-0.1.2.dist-info/RECORD
