Metadata-Version: 2.1
Name: easywsl
Version: 0.1.2
Summary: Easy to deploy WSL.
Home-page: https://github.com/drunkdream/easy-wsl
Author: drunkdream
Author-email: drunkdream@qq.com
License: MIT
Platform: UNKNOWN
Classifier: Development Status :: 3 - Alpha
Classifier: License :: OSI Approved :: MIT License
Classifier: Programming Language :: Python
Classifier: Programming Language :: Python :: 3
Classifier: Programming Language :: Python :: 3.5
Classifier: Programming Language :: Python :: 3.6
Classifier: Programming Language :: Python :: 3.7
Classifier: Programming Language :: Python :: 3.8
Classifier: Intended Audience :: Developers
Requires-Python: >=3.5
Requires-Dist: pywin32
